xradarsat2/__init__.py
xradarsat2/radarSat2_tiff_reader.py
xradarsat2/radarSat2_xarray_reader.py
xradarsat2/utils.py
xradarsat2/xradarsat2-config.yaml
xradarsat2/tests/test_radarSat2_xarray_reader.py
xradarsat2-2025.10.15.dist-info/licenses/LICENSE.md
xradarsat2-2025.10.15.dist-info/METADATA
xradarsat2-2025.10.15.dist-info/WHEEL
xradarsat2-2025.10.15.dist-info/top_level.txt
xradarsat2-2025.10.15.dist-info/RECORD
