Metadata-Version: 2.4
Name: xradarsat2
Version: 2025.10.15
Summary: xarray Level-1 SAR file reader for radarSat2
Author-email: Yann Reynaud <Yann.Reynaud.2@ifremer.fr>
License: MIT
Project-URL: Homepage, https://github.com/umr-lops/xradarsat2
Project-URL: Bug Tracker, https://github.com/umr-lops/xradarsat2/issues
Classifier: Programming Language :: Python :: 3
Classifier: License :: OSI Approved :: MIT License
Classifier: Operating System :: OS Independent
Requires-Python: >=3.9
License-File: LICENSE.md
Requires-Dist: xmltodict
Requires-Dist: numpy
Requires-Dist: xarray>=2024.10.0
Requires-Dist: rasterio
Requires-Dist: rioxarray>=0.18.1
Requires-Dist: dask
Requires-Dist: affine
Requires-Dist: regex
Requires-Dist: pyyaml
Requires-Dist: fsspec
Requires-Dist: aiohttp
Dynamic: license-file
